emmaa/__init__.py
emmaa/analyze_tests_results.py
emmaa/answer_queries.py
emmaa/filter_functions.py
emmaa/model.py
emmaa/model_tests.py
emmaa/queries.py
emmaa/statements.py
emmaa/util.py
emmaa/aws_lambda_functions/__init__.py
emmaa/aws_lambda_functions/after_update.py
emmaa/aws_lambda_functions/email_notifications.py
emmaa/aws_lambda_functions/model_manager_update.py
emmaa/aws_lambda_functions/model_queries.py
emmaa/aws_lambda_functions/model_stats.py
emmaa/aws_lambda_functions/model_tests.py
emmaa/aws_lambda_functions/model_updates.py
emmaa/aws_lambda_functions/test_pipeline.py
emmaa/aws_lambda_functions/test_stats.py
emmaa/aws_lambda_functions/test_update.py
emmaa/aws_lambda_functions/test_update_pipeline.py
emmaa/aws_lambda_functions/update_lambda.py
emmaa/aws_lambda_functions/update_pipeline.py
emmaa/db/__init__.py
emmaa/db/config.py
emmaa/db/constructors.py
emmaa/db/manager.py
emmaa/db/schema.py
emmaa/priors/__init__.py
emmaa/priors/cancer_prior.py
emmaa/priors/gene_list_prior.py
emmaa/priors/literature_prior.py
emmaa/priors/prior_stmts.py
emmaa/priors/reactome_prior.py
emmaa/priors/world_modelers_prior.py
emmaa/readers/__init__.py
emmaa/readers/aws_reader.py
emmaa/readers/db_client_reader.py
emmaa/readers/elsevier_eidos_reader.py
emmaa/subscription/__init__.py
emmaa/subscription/email_service.py
emmaa/subscription/email_util.py
emmaa/subscription/notifications.py
emmaa/tests/__init__.py
emmaa/tests/db_setup.py
emmaa/tests/test_answer_queries.py
emmaa/tests/test_db.py
emmaa/tests/test_db_client_reader.py
emmaa/tests/test_email_service.py
emmaa/tests/test_filters.py
emmaa/tests/test_gene_list_prior.py
emmaa/tests/test_lambda.py
emmaa/tests/test_model.py
emmaa/tests/test_model_tests.py
emmaa/tests/test_notifications.py
emmaa/tests/test_queries.py
emmaa/tests/test_reactome_prior.py
emmaa/tests/test_s3.py
emmaa/tests/test_statements.py
emmaa/tests/test_stats.py
emmaa/tests/test_xdd.py
emmaa/xdd/__init__.py
emmaa/xdd/xdd_client.py
emmaa_service/__init__.py
emmaa-1.17.0.dist-info/LICENSE
emmaa-1.17.0.dist-info/METADATA
emmaa-1.17.0.dist-info/WHEEL
emmaa-1.17.0.dist-info/top_level.txt
emmaa-1.17.0.dist-info/RECORD
