Metadata-Version: 2.1
Name: emmaa
Version: 1.17.0
Summary: Ecosystem of Machine-maintained Models with Automated Analysis
Home-page: https://github.com/indralab/emmaa
Author: EMMAA developers, Harvard Medical School
Author-email: benjamin_gyori@hms.harvard.edu
License: UNKNOWN
Platform: UNKNOWN
Classifier: Development Status :: 4 - Beta
Classifier: Programming Language :: Python :: 3.6
Classifier: Programming Language :: Python :: 3.7
Requires-Dist: indra
Requires-Dist: boto3
Requires-Dist: jsonpickle
Requires-Dist: kappy (==4.0.94)
Requires-Dist: pygraphviz
Requires-Dist: fnvhash
Requires-Dist: sqlalchemy (<1.4)
Requires-Dist: inflection
Requires-Dist: pybel (==0.15)
Requires-Dist: flask-jwt-extended (==3.25.0)
Requires-Dist: gilda
Requires-Dist: tweepy
Provides-Extra: test
Requires-Dist: nose ; extra == 'test'
Requires-Dist: coverage ; extra == 'test'
Requires-Dist: moto[iam] ; extra == 'test'
Requires-Dist: sqlalchemy-utils ; extra == 'test'
